MANIFEST.in
README.rst
setup.cfg
setup.py
docs/.DS_Store
docs/.gitignore
docs/conf.py
docs/index.rst
docs/jobs.rst
docs/profiles.rst
docs/stores.rst
docs/_build/doctrees/environment.pickle
docs/_build/doctrees/index.doctree
docs/_build/doctrees/jobs.doctree
docs/_build/doctrees/profiles.doctree
docs/_build/doctrees/stores.doctree
docs/_build/html/.buildinfo
docs/_build/html/genindex.html
docs/_build/html/index.html
docs/_build/html/jobs.html
docs/_build/html/objects.inv
docs/_build/html/profiles.html
docs/_build/html/search.html
docs/_build/html/searchindex.js
docs/_build/html/stores.html
docs/_build/html/_sources/index.txt
docs/_build/html/_sources/jobs.txt
docs/_build/html/_sources/profiles.txt
docs/_build/html/_sources/stores.txt
docs/_build/html/_static/basic.css
docs/_build/html/_static/default.css
docs/_build/html/_static/doctools.js
docs/_build/html/_static/file.png
docs/_build/html/_static/jquery.js
docs/_build/html/_static/minus.png
docs/_build/html/_static/nature.css
docs/_build/html/_static/plus.png
docs/_build/html/_static/pygments.css
docs/_build/html/_static/searchtools.js
docs/_build/html/_static/underscore.js
hdcloud/__init__.py
hdcloud/base.py
hdcloud/client.py
hdcloud/exceptions.py
hdcloud/jobs.py
hdcloud/profiles.py
hdcloud/stores.py
python_hdcloud.egg-info/PKG-INFO
python_hdcloud.egg-info/SOURCES.txt
python_hdcloud.egg-info/dependency_links.txt
python_hdcloud.egg-info/requires.txt
python_hdcloud.egg-info/top_level.txt
tests/.DS_Store
tests/__init__.py
tests/__init__.pyc
tests/fakeserver.py
tests/fakeserver.pyc
tests/test_base.py
tests/test_base.pyc
tests/test_exceptions.py
tests/test_exceptions.pyc
tests/test_jobs.py
tests/test_jobs.pyc
tests/test_profiles.py
tests/test_profiles.pyc
tests/test_stores.py
tests/test_stores.pyc
tests/utils.py
tests/utils.pyc