Metadata-Version: 1.0
Name: python-hdcloud
Version: 1.0.1
Summary: Client library for the HD Cloud API
Home-page: http://packages.python.org/python-hdcloud
Author: Jacob Kaplan-Moss
Author-email: jacob@jacobian.org
License: BSD
Platform: UNKNOWN
Classifier: Development Status :: 5 - Production/Stable
Classifier: Environment :: Console
Classifier: Intended Audience :: Developers
Classifier: Intended Audience :: Information Technology
Classifier: License :: OSI Approved :: BSD License
Classifier: Operating System :: OS Independent
Classifier: Programming Language :: Python
